Metadata-Version: 1.0
Name: aiosocks2
Version: 0.3.0
Summary: SOCKS proxy client for asyncio and aiohttp
Home-page: https://github.com/ultrafunkamsterdam/aiosocks2
Author: UltrafunkAmsterdam
Author-email: info@blackhatsecurity.nl
License: Apache 2
Platform: UNKNOWN
